<configuration>

  <property>
    <name>yarn.scheduler.capacity.maximum-applications</name>
    <value>1000000</value>
  </property>

  <property>
    <name>yarn.scheduler.capacity.resource-calculator</name>
    <value>org.apache.hadoop.yarn.util.resource.DefaultResourceCalculator</value>
  </property>

  <property>
    <name>yarn.scheduler.capacity.root.queues</name>
    <value>default</value>
  </property>
  
  <property>
    <name>yarn.scheduler.capacity.root.capacity</name>
    <value>100</value>
  </property>

  <property>
    <name>yarn.scheduler.capacity.root.default.capacity</name>
    <value>100</value>
  </property>

  <property>
    <name>yarn.scheduler.capacity.root.default.user-limit-factor</name>
    <value>10</value>
  </property>

  <property>
    <name>yarn.scheduler.capacity.root.default.maximum-capacity</name>
    <value>100</value>
  </property>

</configuration>
